{
  "user": [
    {
      "name": "Juan Pablo Urgelles",
      "username": "Juanpi2022",
      "email": "juan.urgelles92@gmail.com",
      "password": "Juanpi22",
      "phone": "+55210657460",
      "cpf": "066.481.017-92",
      "gender": "homen",
      "address": {
        "cep": "20271-120",
        "rua": "Avenida Paula Sousa",
        "numero": "90",
        "complemento": "apto 24",
        "estado": "RJ",
        "bairro": "Maracanã",
        "cidade": "Rio de Janeiro"
      },
      "id": 1
    }
  ],
  "lista_espera": [
    {
      "name": "Juan Pablo Urgelles",
      "doctor": "Doutora Alice Oliveira Silva",
      "consulta": "Dermatologia",
      "id": 1
    },
    {
      "name": "Juan Pablo Urgelles",
      "doctor": "Doutor Kauan Oliveira Cardoso",
      "consulta": "Oncologia",
      "id": 2
    }
  ]
}
